setup.py
HTMLProcessor/Grabber.py
HTMLProcessor/__init__.py
SimpleThreading/ThreadPool.py
SimpleThreading/ThreadingByFunction.py
SimpleThreading/__init__.py
ThreadDownloader2608.egg-info/PKG-INFO
ThreadDownloader2608.egg-info/SOURCES.txt
ThreadDownloader2608.egg-info/dependency_links.txt
ThreadDownloader2608.egg-info/requires.txt
ThreadDownloader2608.egg-info/top_level.txt