Metadata-Version: 1.0
Name: ThreadDownloader2608
Version: 1.1.0
Summary: My first py dist
Home-page: UNKNOWN
Author: UNKNOWN
Author-email: UNKNOWN
License: UNKNOWN
Platform: UNKNOWN
